tests/__init__.py
tests/conftest.py
tests/test_base_service.py
tests/test_building_service.py
tests/test_client_service.py
tests/test_level_service.py
tests/test_sdk_service.py
tests/test_site_service.py
tests/test_v9_api_service.py
tests/test_dto/__init__.py
tests/test_dto/test_building_dto.py
tests/test_dto/test_client_metadata_dto.py
tests/test_dto/test_create_response_dto.py
tests/test_dto/test_gps_geofence_dto.py
tests/test_dto/test_level_dto.py
tests/test_dto/test_sdk_configuration_dto.py
tests/test_dto/test_site_dto.py
tests/test_utils/__init__.py
tests/test_utils/test_environment_token_service.py
v9_api_toolkit/__init__.py
v9_api_toolkit/api/base_service.py
v9_api_toolkit/api/building_service.py
v9_api_toolkit/api/client_service.py
v9_api_toolkit/api/level_service.py
v9_api_toolkit/api/sdk_service.py
v9_api_toolkit/api/site_service.py
v9_api_toolkit/api/v9_api_service.py
v9_api_toolkit/dto/__init__.py
v9_api_toolkit/dto/building_dto.py
v9_api_toolkit/dto/client_metadata_dto.py
v9_api_toolkit/dto/create_response_dto.py
v9_api_toolkit/dto/gps_geofence_dto.py
v9_api_toolkit/dto/level_dto.py
v9_api_toolkit/dto/sdk_configuration_dto.py
v9_api_toolkit/dto/site_dto.py
v9_api_toolkit/dto/validation.py
v9_api_toolkit/utils/__init__.py
v9_api_toolkit/utils/constants.py
v9_api_toolkit/utils/environment_token_service.py
v9_api_toolkit-0.1.0.dist-info/licenses/LICENSE-PROPRIETARY.md
v9_api_toolkit-0.1.0.dist-info/METADATA
v9_api_toolkit-0.1.0.dist-info/WHEEL
v9_api_toolkit-0.1.0.dist-info/top_level.txt
v9_api_toolkit-0.1.0.dist-info/RECORD
