Metadata-Version: 2.4
Name: v9-api-toolkit
Version: 0.1.0
Summary: A Python package for interacting with the V9 API
Author-email: Serhat Gürgenyatağı <serhat.gurgenyatagi@pointr.tech>
Project-URL: Homepage, https://github.com/pointr/v9_api_toolkit
Project-URL: Bug Tracker, https://github.com/pointr/v9_api_toolkit/issues
Classifier: Programming Language :: Python :: 3
Classifier: Operating System :: OS Independent
Requires-Python: >=3.9
License-File: LICENSE-PROPRIETARY.md
Requires-Dist: requests>=2.25.0
Dynamic: license-file
